model_interpreter/__init__.py
model_interpreter/_version.py
model_interpreter/interpreter.py
model_interpreter-1.1.0.dist-info/LICENSE
model_interpreter-1.1.0.dist-info/METADATA
model_interpreter-1.1.0.dist-info/WHEEL
model_interpreter-1.1.0.dist-info/top_level.txt
model_interpreter-1.1.0.dist-info/RECORD
