Metadata-Version: 2.1
Name: model_interpreter
Version: 1.1.0
Summary: this package contains functionality for reporting on how your ML model is making decisions
Author-email: LV GI Data Science Team <#DataSciencePackages@lv.co.uk>
License: Proprietary
Requires-Python: >=3.9
License-File: LICENSE
Requires-Dist: numpy
Requires-Dist: shap
Requires-Dist: numba>=0.54
Provides-Extra: dev
Requires-Dist: xgboost-cpu; extra == "dev"
Requires-Dist: pytest; extra == "dev"
Requires-Dist: pytest-mock; extra == "dev"
Requires-Dist: pytest-cov; extra == "dev"
Requires-Dist: pytest-benchmark; extra == "dev"
Requires-Dist: hypothesis; extra == "dev"
Requires-Dist: mypy; extra == "dev"
Requires-Dist: ruff; extra == "dev"
Requires-Dist: pre-commit; extra == "dev"
Requires-Dist: scikit-learn; extra == "dev"
Requires-Dist: pandas; extra == "dev"
